odoo8_addon_account_tax_report_no_zeroes-8.0.1.0.0-py2.7-nspkg.pth
odoo_addons/account_tax_report_no_zeroes/__openerp__.py
odoo_addons/account_tax_report_no_zeroes/__init__.py
odoo_addons/account_tax_report_no_zeroes/README.rst
odoo_addons/account_tax_report_no_zeroes/report/__init__.py
odoo_addons/account_tax_report_no_zeroes/report/report_vat.py
odoo_addons/account_tax_report_no_zeroes/static/description/icon.png
odoo8_addon_account_tax_report_no_zeroes-8.0.1.0.0.dist-info/top_level.txt
odoo8_addon_account_tax_report_no_zeroes-8.0.1.0.0.dist-info/WHEEL
odoo8_addon_account_tax_report_no_zeroes-8.0.1.0.0.dist-info/RECORD
odoo8_addon_account_tax_report_no_zeroes-8.0.1.0.0.dist-info/metadata.json
odoo8_addon_account_tax_report_no_zeroes-8.0.1.0.0.dist-info/DESCRIPTION.rst
odoo8_addon_account_tax_report_no_zeroes-8.0.1.0.0.dist-info/METADATA
odoo8_addon_account_tax_report_no_zeroes-8.0.1.0.0.dist-info/namespace_packages.txt
