Metadata-Version: 2.0
Name: odoo8-addon-account-tax-report-no-zeroes
Version: 8.0.1.0.0
Summary: Account tax report without zeroes
Home-page: http://www.serviciosbaeza.com
Author: UNKNOWN
Author-email: UNKNOWN
License: UNKNOWN
Platform: UNKNOWN
Requires-Dist: odoo (<9.0a,>=8.0a)
Classifier: Programming Language :: Python :: 2.7
Classifier: Framework :: Odoo
